hero/__init__.py
hero/event.py
hero/evolver.py
hero/hero.py
hero/hook.py
hero/task.py
hero/build_in_model/__init__.py
hero/build_in_model/deepseek.py
hero/build_in_model/google.py
hero/build_in_model/model.py
hero/build_in_model/rl.py
hero/build_in_tool/__init__.py
hero/build_in_tool/execute_shell.py
hero/build_in_tool/experiment_report.py
hero/build_in_tool/extract_key_info_from_file.py
hero/build_in_tool/final_answer.py
hero/build_in_tool/glob.py
hero/build_in_tool/grep.py
hero/build_in_tool/ls.py
hero/build_in_tool/plan.py
hero/build_in_tool/program.py
hero/build_in_tool/read_file.py
hero/build_in_tool/reflect_and_brainstorm.py
hero/build_in_tool/util.py
hero/build_in_tool/write_a_note.py
hero/build_in_tool/prompt/__init__.py
hero/build_in_tool/prompt/coder.md
hero/build_in_tool/prompt/extractor.md
hero/build_in_tool/prompt/reasoner.py
hero/build_in_tool/prompt/stormer.md
hero/compressor/__init__.py
hero/compressor/compressor.py
hero/other_tool/__init__.py
hero/other_tool/claude_code/__init__.py
hero/other_tool/claude_code/edit.py
hero/other_tool/claude_code/write.py
hero/util/__init__.py
hero/util/constant.py
hero/util/function.py
hero/util/listener_cli.py
hero/util/log.py
hero/util/shell.py
hero/util/test.txt
hero/util/tokenizer/__init__.py
hero/util/tokenizer/deepseek_v3_tokenizer/__init__.py
hero/util/tokenizer/deepseek_v3_tokenizer/deepseek_tokenizer.py
hero/util/tokenizer/deepseek_v3_tokenizer/tokenizer.json
hero/util/tokenizer/deepseek_v3_tokenizer/tokenizer_config.json
hero_core-1.1.2.dist-info/licenses/LICENCE
hero_core-1.1.2.dist-info/METADATA
hero_core-1.1.2.dist-info/WHEEL
hero_core-1.1.2.dist-info/top_level.txt
hero_core-1.1.2.dist-info/RECORD
